setup.py
./moving_pictures/__init__.py
./moving_pictures/example_morpho.py
./moving_pictures/moving_pictures.py
moving_pictures.egg-info/PKG-INFO
moving_pictures.egg-info/SOURCES.txt
moving_pictures.egg-info/dependency_links.txt
moving_pictures.egg-info/top_level.txt